[
  {
    "name": "Bigetron RA",
    "countryCode": "id",
    "players": [],
    "region": "Other",
    "qualification": "Global Stage"
  },
  {
    "name": "Futbolist",
    "countryCode": "tr",
    "players": [
      "Solkay",
      "Lova"
    ],
    "region": "Other",
    "qualification": "Global Stage"
  },
  {
    "name": "Elites United Team",
    "countryCode": "ph",
    "players": [
      "VeryGood",
      "VeryYummy",
      "47",
      "VeryNice",
      "BERNA",
      "Krey"
    ],
    "region": "Other",
    "qualification": "Host Country Invite"
  },
  {
    "name": "Aerowolf LIMAX",
    "countryCode": "id",
    "players": [],
    "region": "Other",
    "qualification": "Global Stage"
  },
  {
    "name": "Secret Jin",
    "countryCode": "th",
    "players": [],
    "region": "Other",
    "qualification": "Global Stage"
  },
  {
    "name": "RRQ Athena",
    "countryCode": "th",
    "players": [
      "G9",
      "D2E",
      "Senior",
      "Earnny",
      "Beer11"
    ],
    "region": "SEA",
    "qualification": "PUBG_Mobile_Pro_League/Southeast_Asia/Season_2"
  },
  {
    "name": "POWER888 KPS",
    "countryCode": "th",
    "players": [
      "Korpaii",
      "Ices",
      "TT",
      "Gewwy",
      "2Stop"
    ],
    "region": "Other",
    "qualification": "Global Stage"
  },
  {
    "name": "Team Secret",
    "countryCode": "my",
    "players": [
      "iShot"
    ],
    "region": "Other",
    "qualification": "Global Stage"
  },
  {
    "name": "Abrupt Slayers",
    "countryCode": "np",
    "players": [
      "HeavenXD",
      "King",
      "Charii",
      "JokeR",
      "NovaX",
      "Leon"
    ],
    "region": "SEA",
    "qualification": "PUBG_Mobile_Pro_League/South_Asia/Season_2"
  },
  {
    "name": "DRS GAMING",
    "countryCode": "np",
    "players": [
      "MafiaNinja",
      "Nima",
      "AJ",
      "Gyal"
    ],
    "region": "Other",
    "qualification": "Global Stage"
  },
  {
    "name": "A1 eSports",
    "countryCode": "bd",
    "players": [
      "SiNiSTER",
      "Shoikot",
      "DANTE",
      "6NiN3",
      "RxJax"
    ],
    "region": "SEA",
    "qualification": "PUBG_Mobile_Pro_League/South_Asia/Season_2"
  },
  {
    "name": "Loops",
    "countryCode": "br",
    "players": [
      "Dadin",
      "Caiowski",
      "Gxlden",
      "Carrilho",
      "Federal"
    ],
    "region": "SEA",
    "qualification": "PUBG_Mobile_Pro_League/Americas/Season_2"
  },
  {
    "name": "The Unnamed",
    "countryCode": "vn",
    "players": [
      "Bucky",
      "PiuPiu",
      "Ran",
      "Ravenn",
      "KingG"
    ],
    "region": "SEA",
    "qualification": "PUBG_Mobile_Pro_League/Americas/Season_2"
  },
  {
    "name": "Execute Esports",
    "countryCode": "us",
    "players": [
      "ItsFate",
      "KillSwitch",
      "Echooo",
      "FameBoi"
    ],
    "region": "Other",
    "qualification": "Global Stage"
  },
  {
    "name": "A7 eSports",
    "countryCode": "br",
    "players": [
      "Law",
      "Senab",
      "Swaguin",
      "ViTU2K",
      "Mafioso"
    ],
    "region": "SEA",
    "qualification": "PUBG_Mobile_Pro_League/Americas/Season_2"
  },
  {
    "name": "Natus Vincere",
    "countryCode": "un",
    "players": [
      "OldBoy",
      "Tix"
    ],
    "region": "Other",
    "qualification": "Global Stage"
  },
  {
    "name": "Klas Digital Athletics",
    "countryCode": "tr",
    "players": [
      "SeLim",
      "Ray"
    ],
    "region": "Other",
    "qualification": "Global Stage"
  },
  {
    "name": "GODSENT",
    "countryCode": "eu",
    "players": [
      "marley",
      "rolkis",
      "reeves"
    ],
    "region": "Other",
    "qualification": "Global Stage"
  },
  {
    "name": "Konina Power",
    "countryCode": "un",
    "players": [],
    "region": "Other",
    "qualification": "Global Stage"
  },
  {
    "name": "Four Angry Men",
    "countryCode": "cn",
    "players": [
      "Suk",
      "33Svan",
      "Hasaki",
      "Xinhe",
      "QingChen"
    ],
    "region": "PEL",
    "qualification": "Peacekeeper_Elite_League/2020/Points#Results"
  },
  {
    "name": "Nova Esports",
    "countryCode": "cn",
    "players": [
      "Coolboy",
      "Jimmy",
      "King",
      "Paraboy",
      "Order"
    ],
    "region": "PEL",
    "qualification": "Peacekeeper_Elite_League/2020/Points"
  },
  {
    "name": "BLUE BEES",
    "countryCode": "jp",
    "players": [
      "ReijiOcO",
      "aitochan",
      "Devine",
      "sQxuOcO",
      "Lufa"
    ],
    "region": "SEA",
    "qualification": "PUBG_Mobile_Japan_League/Season_0"
  },
  {
    "name": "Archer Gaming",
    "countryCode": "kr",
    "players": [
      "EunSu",
      "Ssung",
      "FAVIAN",
      "InonixOvO"
    ],
    "region": "Other",
    "qualification": "PUBG_Mobile_Street_Challenge/2020/Fall"
  },
  {
    "name": "Zeus Esports",
    "countryCode": "mn",
    "players": [],
    "region": "Other",
    "qualification": "Global Stage"
  }
]